django_nitro_mailer/__init__.py
django_nitro_mailer/admin.py
django_nitro_mailer/apps.py
django_nitro_mailer/array_field.py
django_nitro_mailer/backends.py
django_nitro_mailer/defaults.py
django_nitro_mailer/emails.py
django_nitro_mailer/forms.py
django_nitro_mailer/models.py
django_nitro_mailer/utils.py
django_nitro_mailer/locale/pl/LC_MESSAGES/django.mo
django_nitro_mailer/locale/pl/LC_MESSAGES/django.po
django_nitro_mailer/management/__init__.py
django_nitro_mailer/management/commands/__init__.py
django_nitro_mailer/management/commands/nitro_send_emails.py
django_nitro_mailer/migrations/0001_initial_squashed.py
django_nitro_mailer/migrations/__init__.py
django_nitro_mailer/templates/django_nitro_mailer/admin/email_change_form.html
django_nitro_mailer-0.2.0.dist-info/licenses/LICENSE
django_nitro_mailer-0.2.0.dist-info/METADATA
django_nitro_mailer-0.2.0.dist-info/WHEEL
django_nitro_mailer-0.2.0.dist-info/top_level.txt
django_nitro_mailer-0.2.0.dist-info/RECORD
