Metadata-Version: 2.4
Name: django-nitro-mailer
Version: 0.2.0
Summary: Django mails. Supercharged.
Author-email: Kamil Marut <kamil@kamilmarut.com>
License-Expression: MIT
Requires-Python: <3.14,>=3.11
License-File: LICENSE
Requires-Dist: django<6.1,>=5.2
Dynamic: license-file
